coderag/__init__.py
coderag/cli.py
coderag/config.py
coderag/logging.py
coderag/main.py
coderag/api/__init__.py
coderag/api/routes.py
coderag/api/schemas.py
coderag/generation/__init__.py
coderag/generation/citations.py
coderag/generation/generator.py
coderag/generation/prompts.py
coderag/indexing/__init__.py
coderag/indexing/embeddings.py
coderag/indexing/vectorstore.py
coderag/ingestion/__init__.py
coderag/ingestion/chunker.py
coderag/ingestion/filter.py
coderag/ingestion/loader.py
coderag/ingestion/validator.py
coderag/mcp/__init__.py
coderag/mcp/cli.py
coderag/mcp/handlers.py
coderag/mcp/prompts.py
coderag/mcp/resources.py
coderag/mcp/server.py
coderag/mcp/tools.py
coderag/models/__init__.py
coderag/models/chunk.py
coderag/models/document.py
coderag/models/query.py
coderag/models/repository.py
coderag/models/response.py
coderag/retrieval/__init__.py
coderag/retrieval/retriever.py
coderag/ui/__init__.py
coderag/ui/app.py
coderag/ui/handlers.py
code_rag_me-0.1.2.dist-info/METADATA
code_rag_me-0.1.2.dist-info/WHEEL
code_rag_me-0.1.2.dist-info/entry_points.txt
code_rag_me-0.1.2.dist-info/licenses/LICENSE
code_rag_me-0.1.2.dist-info/RECORD
