Metadata-Version: 2.4
Name: code-rag-me
Version: 0.1.2
Summary: RAG-based Q&A system for code repositories with verifiable citations
Project-URL: Homepage, https://github.com/Sebastiangmz/CodeRAG
Project-URL: Repository, https://github.com/Sebastiangmz/CodeRAG
Author-email: Sebastian <segamozi@gmail.com>
License-Expression: MIT
License-File: LICENSE
Keywords: chromadb,code,embeddings,llm,qa,rag
Classifier: Development Status :: 3 - Alpha
Classifier: Intended Audience :: Developers
Classifier: License :: OSI Approved :: MIT License
Classifier: Programming Language :: Python :: 3.11
Classifier: Programming Language :: Python :: 3.12
Requires-Python: >=3.11
Requires-Dist: accelerate>=1.1.0
Requires-Dist: bitsandbytes>=0.44.0
Requires-Dist: chromadb>=0.5.0
Requires-Dist: click>=8.1.0
Requires-Dist: einops>=0.8.0
Requires-Dist: fastapi>=0.115.0
Requires-Dist: gitpython>=3.1.0
Requires-Dist: gradio>=4.44.0
Requires-Dist: httpx>=0.27.0
Requires-Dist: mcp>=1.0.0
Requires-Dist: openai>=1.50.0
Requires-Dist: pydantic-settings>=2.6.0
Requires-Dist: pydantic>=2.10.0
Requires-Dist: python-dotenv>=1.0.0
Requires-Dist: pyyaml>=6.0.0
Requires-Dist: sentence-transformers>=3.3.0
Requires-Dist: structlog>=24.4.0
Requires-Dist: torch>=2.5.0
Requires-Dist: transformers>=4.46.0
Requires-Dist: tree-sitter-python>=0.23.0
Requires-Dist: tree-sitter>=0.23.0
Requires-Dist: uvicorn[standard]>=0.32.0
Provides-Extra: dev
Requires-Dist: black>=24.10.0; extra == 'dev'
Requires-Dist: mypy>=1.13.0; extra == 'dev'
Requires-Dist: pre-commit>=4.0.0; extra == 'dev'
Requires-Dist: pytest-asyncio>=0.24.0; extra == 'dev'
Requires-Dist: pytest-cov>=6.0.0; extra == 'dev'
Requires-Dist: pytest>=8.3.0; extra == 'dev'
Requires-Dist: ruff>=0.8.0; extra == 'dev'
